{
    "now": "2024-12-26T06:09:58.024Z",
    "perfNow": 120813.40000000596,
    "diagnosticCorrelation": "d2d6ccb3-955c-49cb-8b80-3634d0f16b93",
    "source": "DownloadSupportFiles",
    "environment": {
        "productName": "adf",
        "buildVersion": "1.0.110124.1",
        "environmentType": 3,
        "resourceName": "gravity-adf-01",
        "resourceRegion": "westeurope",
        "resourceGroup": "DEV-WEU-DataPlatform-Gravity-rg",
        "subscriptionId": "3cb8b38c-c13b-4e3a-9f4b-0dc64b660ee5",
        "sessionId": "VFGWeLuQ4ELkdsk1gVek7m",
        "operationId": "",
        "gitType": "live",
        "loggingKey": "4228136e-5d84-4d7c-b7cc-c080a14b1bf4"
    },
    "additionalInfo": {
        "selectedResource": "PL_AE_ HOURLY",
        "selectedResourceType": "pipeline"
    }
}